.gitignore
.pylintrc
AUTHORS.txt
CHANGELOG.rst
CONTRIBUTING.rst
LICENSE.txt
MANIFEST.in
README.rst
pyproject.toml
setup.py
tox.ini
.github/workflows/publish-sdist.yml
.github/workflows/run-tox.yml
atlas_densities/__init__.py
atlas_densities/exceptions.py
atlas_densities/utils.py
atlas_densities/version.py
atlas_densities.egg-info/PKG-INFO
atlas_densities.egg-info/SOURCES.txt
atlas_densities.egg-info/dependency_links.txt
atlas_densities.egg-info/entry_points.txt
atlas_densities.egg-info/requires.txt
atlas_densities.egg-info/top_level.txt
atlas_densities/app/__init__.py
atlas_densities/app/cell_densities.py
atlas_densities/app/cli.py
atlas_densities/app/combination.py
atlas_densities/app/mtype_densities.py
atlas_densities/app/utils.py
atlas_densities/app/data/1.json
atlas_densities/app/data/__init__.py
atlas_densities/app/data/markers/README.rst
atlas_densities/app/data/markers/combine_markers_ccfv2_config.yaml
atlas_densities/app/data/markers/fit_average_densities_ccfv2_config.yaml
atlas_densities/app/data/markers/realigned_slices_bbp.json
atlas_densities/app/data/markers/realigned_slices_ccfv2.json
atlas_densities/app/data/measurements/README.rst
atlas_densities/app/data/measurements/gaba_papers.xlsx
atlas_densities/app/data/measurements/homogenous_regions.csv
atlas_densities/app/data/measurements/measurements.csv
atlas_densities/app/data/measurements/mmc1.xlsx
atlas_densities/app/data/measurements/mmc3.xlsx
atlas_densities/app/data/measurements/non_density_measurements.csv
atlas_densities/app/data/measurements/std_cells.json
atlas_densities/app/data/metadata/README.txt
atlas_densities/app/data/metadata/ca1_metadata.json
atlas_densities/app/data/metadata/excitatory-inhibitory-splitting.json
atlas_densities/app/data/metadata/group_ids.json
atlas_densities/app/data/metadata/isocortex_23_metadata.json
atlas_densities/app/data/metadata/isocortex_metadata.json
atlas_densities/app/data/metadata/metadata.json
atlas_densities/app/data/metadata/thalamus_metadata.json
atlas_densities/app/data/mtypes/mapping_cortex_all_to_exc_mtypes.csv
atlas_densities/app/data/mtypes/mtypes_probability_map_config.yaml
atlas_densities/app/data/mtypes/composition/README.rst
