Metadata-Version: 2.1
Name: atlas-densities
Version: 0.2.6
Summary: Library containing command lines and tools to compute volumetric cell densities in the rodent brain
Home-page: https://github.com/BlueBrain/atlas-densities
Author: Blue Brain Project, EPFL
License: Apache-2
Download-URL: https://github.com/BlueBrain/atlas-densities
Platform: UNKNOWN
Classifier: Development Status :: 2 - Pre-Alpha
Classifier: Programming Language :: Python
Classifier: Programming Language :: Python :: 3
Classifier: Programming Language :: Python :: 3.8
Classifier: Programming Language :: Python :: 3.9
Classifier: Programming Language :: Python :: 3.10
Requires-Python: >=3.7.0
Provides-Extra: tests
